{
	"info": {
		"_postman_id": "910d9684-44e9-4e2d-b52d-62284cd7b5e8",
		"name": "oop_1",
		"schema": "https://schema.getpostman.com/json/collection/v2.1.0/collection.json"
	},
	"item": [
		{
			"name": "list_acc",
			"request": {
				"method": "GET",
				"header": [],
				"url": {
					"raw": "http://127.0.0.1:8686/account",
					"protocol": "http",
					"host": [
						"127",
						"0",
						"0",
						"1"
					],
					"port": "8686",
					"path": [
						"account"
					]
				}
			},
			"response": []
		},
		{
			"name": "add_acc",
			"request": {
				"method": "POST",
				"header": [],
				"body": {
					"mode": "raw",
					"raw": "{\r\n    \"name\":\"\",\r\n    \"amount\": ,\r\n    \"number\":\"\"\r\n}",
					"options": {
						"raw": {
							"language": "json"
						}
					}
				},
				"url": {
					"raw": "http://127.0.0.1:8686/add_acc",
					"protocol": "http",
					"host": [
						"127",
						"0",
						"0",
						"1"
					],
					"port": "8686",
					"path": [
						"add_acc"
					]
				}
			},
			"response": []
		},
		{
			"name": "deposit",
			"request": {
				"method": "POST",
				"header": [],
				"body": {
					"mode": "raw",
					"raw": "{\r\n    \"number\":\"\",\r\n    \"money\": \r\n}",
					"options": {
						"raw": {
							"language": "json"
						}
					}
				},
				"url": {
					"raw": "http://127.0.0.1:8686/deposit",
					"protocol": "http",
					"host": [
						"127",
						"0",
						"0",
						"1"
					],
					"port": "8686",
					"path": [
						"deposit"
					]
				}
			},
			"response": []
		},
		{
			"name": "withdrawal",
			"request": {
				"method": "POST",
				"header": [],
				"body": {
					"mode": "raw",
					"raw": "{\r\n    \"number\":\"\",\r\n    \"money\":\r\n}",
					"options": {
						"raw": {
							"language": "json"
						}
					}
				},
				"url": {
					"raw": "http://127.0.0.1:8686/withdrawal",
					"protocol": "http",
					"host": [
						"127",
						"0",
						"0",
						"1"
					],
					"port": "8686",
					"path": [
						"withdrawal"
					]
				}
			},
			"response": []
		}
	]
}